spe_xps_reader/__init__.py
spe_xps_reader/__main__.py
spe_xps_reader/reader.py
spe_xps_reader-1.0.0.dist-info/licenses/LICENSE
spe_xps_reader-1.0.0.dist-info/METADATA
spe_xps_reader-1.0.0.dist-info/WHEEL
spe_xps_reader-1.0.0.dist-info/entry_points.txt
spe_xps_reader-1.0.0.dist-info/top_level.txt
spe_xps_reader-1.0.0.dist-info/RECORD
