Metadata-Version: 2.4
Name: spe-xps-reader
Version: 1.0.0
Summary: A Python library for reading PHI Instruments SPE files for XPS data analysis
Author: Gwilherm Kerherve
Project-URL: Homepage, https://github.com/gkerherve/spe-xps-reader
Project-URL: Documentation, https://github.com/gkerherve/spe-xps-reader/blob/main/README.md
Project-URL: Repository, https://github.com/gkerherve/spe-xps-reader
Project-URL: Bug Tracker, https://github.com/gkerherve/spe-xps-reader/issues
Project-URL: Changelog, https://github.com/gkerherve/spe-xps-reader/blob/main/CHANGELOG.md
Keywords: XPS,spectroscopy,PHI,SPE,scientific-data,materials-science,surface-science,photoelectron-spectroscopy
Classifier: Development Status :: 5 - Production/Stable
Classifier: Intended Audience :: Science/Research
Classifier: Topic :: Scientific/Engineering :: Chemistry
Classifier: Topic :: Scientific/Engineering :: Physics
Classifier: License :: OSI Approved :: GNU General Public License v3 (GPLv3)
Classifier: Programming Language :: Python :: 3
Classifier: Programming Language :: Python :: 3.6
Classifier: Programming Language :: Python :: 3.7
Classifier: Programming Language :: Python :: 3.8
Classifier: Programming Language :: Python :: 3.9
Classifier: Programming Language :: Python :: 3.10
Classifier: Programming Language :: Python :: 3.11
Classifier: Programming Language :: Python :: 3.12
Classifier: Operating System :: OS Independent
Requires-Python: >=3.6
License-File: LICENSE
Requires-Dist: numpy>=1.16.0
Provides-Extra: dev
Requires-Dist: matplotlib>=3.0.0; extra == "dev"
Requires-Dist: pytest>=6.0.0; extra == "dev"
Dynamic: license-file
